ezfs.py
ezfs-1.1.1.dist-info/LICENSE
ezfs-1.1.1.dist-info/METADATA
ezfs-1.1.1.dist-info/WHEEL
ezfs-1.1.1.dist-info/top_level.txt
ezfs-1.1.1.dist-info/RECORD
