Metadata-Version: 2.1
Name: ezfs
Version: 1.1.1
Summary: Minimalistic virtual filesystem adapters for Python
Author: David Fritz
License: MIT
Project-URL: Home, https://github.com/pyranha-labs/ezfs
Project-URL: Changelog, https://github.com/pyranha-labs/ezfs/releases
Project-URL: Issues, https://github.com/pyranha-labs/ezfs/issues
Keywords: filesystem,s3,compression
Platform: MacOS
Platform: Linux
Platform: Windows
Classifier: Development Status :: 5 - Production/Stable
Classifier: Intended Audience :: Developers
Classifier: License :: OSI Approved :: MIT License
Classifier: Programming Language :: Python
Classifier: Programming Language :: Python :: 3
Classifier: Programming Language :: Python :: 3 :: Only
Classifier: Programming Language :: Python :: 3.10
Classifier: Programming Language :: Python :: 3.11
Classifier: Programming Language :: Python :: 3.12
Classifier: Topic :: Software Development
Classifier: Topic :: System :: Filesystems
Classifier: Typing :: Typed
Classifier: Operating System :: MacOS
Classifier: Operating System :: Microsoft :: Windows
Classifier: Operating System :: POSIX :: Linux
Requires-Python: >=3.10
License-File: LICENSE
Provides-Extra: blosc
Requires-Dist: blosc ; extra == 'blosc'
Provides-Extra: brotli
Requires-Dist: brotli ; extra == 'brotli'
Provides-Extra: lz4
Requires-Dist: lz4 ; extra == 'lz4'
Provides-Extra: s3
Requires-Dist: boto3 ; extra == 's3'
Provides-Extra: snappy
Requires-Dist: python-snappy ; extra == 'snappy'
Provides-Extra: zstd
Requires-Dist: zstandard ; extra == 'zstd'
